{"id":"501981c3-5ca0-4baa-babb-add9e6b8501f","year":2002,"type":"PST","name":"PST","weeks":[{"id":"ec64a98e-b533-4df7-a6c3-1348da7c9158","sequence":1,"title":"1","games":[{"id":"1b162b52-6637-4c56-9891-72ecf5b50d54","status":"closed","scheduled":"2003-01-05T21:47:11+00:00","attendance":66318,"utc_offset":-8,"entry_mode":"INGEST","venue":{"id":"6701808c-c329-482b-9834-2d29cb3185ff","name":"Candlestick Park","city":"San Francisco","state":"CA","country":"USA","zip":"94124","address":"602 Jamestown Avenue","capacity":69732,"surface":"turf","roof_type":"outdoor","sr_id":"sr:venue:8201"},"home":{"id":"f0e724b0-4cbf-495a-be47-013907608da9","name":"San Francisco 49ers","alias":"SF","game_number":1,"sr_id":"sr:competitor:4389"},"away":{"id":"04aa1c9d-66da-489d-b16a-1dee3f2eec4d","name":"New York Giants","alias":"NYG","game_number":1,"sr_id":"sr:competitor:4426"},"scoring":{"home_points":39,"away_points":38,"periods":[{"period_type":"quarter","id":"3546c771-a5cb-4153-8a7e-3c719e3caa48","number":1,"sequence":1,"home_points":7,"away_points":7},{"period_type":"quarter","id":"ed621f12-2345-428b-b87b-255aea1c3874","number":2,"sequence":2,"home_points":7,"away_points":21},{"period_type":"quarter","id":"f913c3c0-b479-4b03-ad98-555528d9a89e","number":3,"sequence":3,"home_points":8,"away_points":10},{"period_type":"quarter","id":"e430a797-2155-4852-8842-dacec2ae325a","number":4,"sequence":4,"home_points":17,"away_points":0}]}},{"id":"98cfc11b-9aad-46fa-9f62-689ad6c073c1","status":"closed","scheduled":"2003-01-05T01:09:01+00:00","attendance":65358,"utc_offset":-6,"entry_mode":"INGEST","venue":{"id":"5a60dd3a-302c-41c6-ab0f-dd335c1103c2","name":"Lambeau Field","city":"Green Bay","state":"WI","country":"USA","zip":"54304","address":"1265 Lombardi Avenue","capacity":81435,"surface":"turf","roof_type":"outdoor","sr_id":"sr:venue:8183","location":{"lat":"44.501357","lng":"-88.062440"}},"home":{"id":"a20471b4-a8d9-40c7-95ad-90cc30e46932","name":"Green Bay Packers","alias":"GB","game_number":1,"sr_id":"sr:competitor:4420"},"away":{"id":"e6aa13a4-0055-48a9-bc41-be28dc106929","name":"Atlanta Falcons","alias":"ATL","game_number":1,"sr_id":"sr:competitor:4393"},"scoring":{"home_points":7,"away_points":27,"periods":[{"period_type":"quarter","id":"99460c46-3a17-478b-a25f-a5129a8b9205","number":1,"sequence":1,"home_points":0,"away_points":14},{"period_type":"quarter","id":"68e4390b-9d48-44e7-b0ca-6f31955645a7","number":2,"sequence":2,"home_points":0,"away_points":10},{"period_type":"quarter","id":"76e92736-ea50-4fb4-b152-d12736e6c4c3","number":3,"sequence":3,"home_points":7,"away_points":3},{"period_type":"quarter","id":"70f87b99-aba7-42b1-b342-7a1f153f1296","number":4,"sequence":4,"home_points":0,"away_points":0}]}},{"id":"ae74f3a3-32fa-44f6-9261-165fd5f2f4c9","status":"closed","scheduled":"2003-01-04T21:41:17+00:00","attendance":78524,"utc_offset":-5,"entry_mode":"INGEST","venue":{"id":"41397549-49d0-4e0f-aad3-6c82cf0214a7","name":"Giants Stadium","city":"East Rutherford","state":"NJ","zip":"07073","address":"50 Route 120","capacity":80242,"surface":"artificial","roof_type":"outdoor","sr_id":"sr:venue:23648"},"home":{"id":"5fee86ae-74ab-4bdd-8416-42a9dd9964f3","name":"New York Jets","alias":"NYJ","game_number":1,"sr_id":"sr:competitor:4427"},"away":{"id":"82cf9565-6eb9-4f01-bdbd-5aa0d472fcd9","name":"Indianapolis Colts","alias":"IND","game_number":1,"sr_id":"sr:competitor:4421"},"scoring":{"home_points":41,"away_points":0,"periods":[{"period_type":"quarter","id":"8981a495-7871-45d5-9470-61a5ec6e798d","number":1,"sequence":1,"home_points":7,"away_points":0},{"period_type":"quarter","id":"48c79a69-738b-4dcb-a45c-39aa8de1bc0f","number":2,"sequence":2,"home_points":17,"away_points":0},{"period_type":"quarter","id":"ca86fac8-0665-49ea-9ede-35fc709d07a3","number":3,"sequence":3,"home_points":10,"away_points":0},{"period_type":"quarter","id":"9d6acb80-775a-4d8b-b72c-965f5206ca51","number":4,"sequence":4,"home_points":7,"away_points":0}]}},{"id":"c1f53f41-8019-460b-81a4-0ae5cb26a31d","status":"closed","scheduled":"2003-01-05T18:14:12+00:00","attendance":62595,"utc_offset":-5,"entry_mode":"INGEST","venue":{"id":"7349a2e6-0ac9-410b-8bd2-ca58c9f7aa34","name":"Heinz Field","city":"Pittsburgh","state":"PA","country":"USA","zip":"15212","address":"100 Art Rooney Avenue","capacity":68400,"surface":"turf","roof_type":"outdoor","sr_id":"sr:venue:8197","location":{"lat":"40.446653","lng":"-80.015844"}},"home":{"id":"cb2f9f1f-ac67-424e-9e72-1475cb0ed398","name":"Pittsburgh Steelers","alias":"PIT","game_number":1,"sr_id":"sr:competitor:4345"},"away":{"id":"d5a2eb42-8065-4174-ab79-0a6fa820e35e","name":"Cleveland Browns","alias":"CLE","game_number":1,"sr_id":"sr:competitor:4417"},"scoring":{"home_points":36,"away_points":33,"periods":[{"period_type":"quarter","id":"74765f77-3b14-4360-b132-a56e47e5adbd","number":1,"sequence":1,"home_points":0,"away_points":7},{"period_type":"quarter","id":"92cd6ba5-0993-4ff8-8190-a4cd40f5a743","number":2,"sequence":2,"home_points":7,"away_points":10},{"period_type":"quarter","id":"9120aad9-8041-402c-b478-f666e8033e9c","number":3,"sequence":3,"home_points":7,"away_points":7},{"period_type":"quarter","id":"41180ff2-bd03-471d-aac4-4f9e533ce027","number":4,"sequence":4,"home_points":22,"away_points":9}]}}]},{"id":"2216cf25-4d3e-4676-aa12-3809ceaa83eb","sequence":2,"title":"2","games":[{"id":"064108ff-3555-41af-a25a-fa00a15f4538","status":"closed","scheduled":"2003-01-12T01:21:45+00:00","attendance":66452,"utc_offset":-5,"entry_mode":"INGEST","venue":{"id":"905f3091-107b-4e7d-af70-2e3822c09aee","name":"Veterans Stadium","city":"Philadelphia","state":"PA","zip":"19148","address":"3501 South Broad Street","capacity":65352,"surface":"artificial","roof_type":"outdoor","sr_id":"sr:venue:1825"},"home":{"id":"386bdbf9-9eea-4869-bb9a-274b0bc66e80","name":"Philadelphia Eagles","alias":"PHI","game_number":1,"sr_id":"sr:competitor:4428"},"away":{"id":"e6aa13a4-0055-48a9-bc41-be28dc106929","name":"Atlanta Falcons","alias":"ATL","game_number":2,"sr_id":"sr:competitor:4393"},"scoring":{"home_points":20,"away_points":6,"periods":[{"period_type":"quarter","id":"4a497e4c-41bb-40ee-8ed7-06b0b1acf790","number":1,"sequence":1,"home_points":10,"away_points":0},{"period_type":"quarter","id":"4246a386-ef81-42dd-8c85-2dc24cfd1762","number":2,"sequence":2,"home_points":3,"away_points":6},{"period_type":"quarter","id":"7635d16c-038a-4055-b0d2-2ceaa7e34e31","number":3,"sequence":3,"home_points":0,"away_points":0},{"period_type":"quarter","id":"e7689902-71d3-45ec-9764-08253fb47e5c","number":4,"sequence":4,"home_points":7,"away_points":0}]}},{"id":"2b4ce39e-be55-4e12-a0dd-a9fec7010ac8","status":"closed","scheduled":"2003-01-12T21:45:24+00:00","attendance":62207,"utc_offset":-8,"entry_mode":"INGEST","venue":{"id":"ba1ad00f-9130-462c-93f9-5612a0015117","name":"RingCentral Coliseum","city":"Oakland","state":"CA","country":"USA","zip":"94621","address":"7000 Coliseum Way","capacity":53286,"surface":"turf","roof_type":"outdoor","sr_id":"sr:venue:8095","location":{"lat":"37.750342","lng":"-122.202806"}},"home":{"id":"1c1cec48-6352-4556-b789-35304c1a6ae1","name":"Oakland Raiders","alias":"OAK","game_number":1,"sr_id":"sr:competitor:4390"},"away":{"id":"5fee86ae-74ab-4bdd-8416-42a9dd9964f3","name":"New York Jets","alias":"NYJ","game_number":2,"sr_id":"sr:competitor:4427"},"scoring":{"home_points":30,"away_points":10,"periods":[{"period_type":"quarter","id":"d864ddaf-9859-4660-a396-2370e3555b44","number":1,"sequence":1,"home_points":3,"away_points":3},{"period_type":"quarter","id":"597d29f8-a287-44ab-9e13-056deb87f7c6","number":2,"sequence":2,"home_points":7,"away_points":7},{"period_type":"quarter","id":"953c4011-e19c-4c7e-9c82-165efe32b5fb","number":3,"sequence":3,"home_points":7,"away_points":0},{"period_type":"quarter","id":"9812662f-d641-4d8f-8074-39e28323f2a0","number":4,"sequence":4,"home_points":13,"away_points":0}]}},{"id":"8279b72e-fa32-46ec-8e69-6f6a69926b91","status":"closed","scheduled":"2003-01-12T18:07:22+00:00","attendance":65599,"utc_offset":-5,"entry_mode":"INGEST","venue":{"id":"6fccc39c-80bc-4c81-83d9-2d5a848c8c09","name":"Raymond James Stadium","city":"Tampa","state":"FL","country":"USA","zip":"33607","address":"4201 North Dale Mabry Highway","capacity":65890,"surface":"turf","roof_type":"outdoor","sr_id":"sr:venue:8205","location":{"lat":"27.976211","lng":"-82.503625"}},"home":{"id":"4254d319-1bc7-4f81-b4ab-b5e6f3402b69","name":"Tampa Bay Buccaneers","alias":"TB","game_number":1,"sr_id":"sr:competitor:4388"},"away":{"id":"f0e724b0-4cbf-495a-be47-013907608da9","name":"San Francisco 49ers","alias":"SF","game_number":2,"sr_id":"sr:competitor:4389"},"scoring":{"home_points":31,"away_points":6,"periods":[{"period_type":"quarter","id":"e862585b-53cf-43a9-9b42-98f42ebbcd6d","number":1,"sequence":1,"home_points":7,"away_points":3},{"period_type":"quarter","id":"2ccc94f6-ebb9-4a32-ac9e-4f1518fa9cd4","number":2,"sequence":2,"home_points":21,"away_points":3},{"period_type":"quarter","id":"c2581587-5ebb-4477-bb8c-54559de90106","number":3,"sequence":3,"home_points":3,"away_points":0},{"period_type":"quarter","id":"0e432210-cab4-41f6-966d-62459f139680","number":4,"sequence":4,"home_points":0,"away_points":0}]}},{"id":"bd780f17-59b1-4a29-be33-4097db0bee8f","status":"closed","scheduled":"2003-01-11T21:37:23+00:00","attendance":68809,"utc_offset":-6,"entry_mode":"INGEST","venue":{"id":"5295c1b7-c85c-49cb-9569-1707c65324e5","name":"Nissan Stadium","city":"Nashville","state":"TN","country":"USA","zip":"37213","address":"One Titans Way","capacity":69143,"surface":"turf","roof_type":"outdoor","sr_id":"sr:venue:8207","location":{"lat":"36.166367","lng":"-86.771223"}},"home":{"id":"d26a1ca5-722d-4274-8f97-c92e49c96315","name":"Tennessee Titans","alias":"TEN","game_number":1,"sr_id":"sr:competitor:367364"},"away":{"id":"cb2f9f1f-ac67-424e-9e72-1475cb0ed398","name":"Pittsburgh Steelers","alias":"PIT","game_number":2,"sr_id":"sr:competitor:4345"},"scoring":{"home_points":34,"away_points":31,"periods":[{"period_type":"quarter","id":"f213530c-0b20-4214-92b4-e2c7356736e3","number":1,"sequence":1,"home_points":14,"away_points":0},{"period_type":"quarter","id":"52de6436-a909-4e24-a463-dbc4d767892c","number":2,"sequence":2,"home_points":0,"away_points":13},{"period_type":"quarter","id":"82f06484-cb19-4e3d-8d2f-ab012a9f6946","number":3,"sequence":3,"home_points":14,"away_points":7},{"period_type":"quarter","id":"83b701ca-ea4a-4c0f-a5ec-dfc0324b32ab","number":4,"sequence":4,"home_points":3,"away_points":11},{"period_type":"overtime","id":"2a9abee4-5c27-44f0-9a94-3a635647106c","number":1,"sequence":5,"home_points":3,"away_points":0}]}}]},{"id":"b8cc732f-76b7-47f8-9fcb-c1c722f0974c","sequence":3,"title":"3","games":[{"id":"088c0c62-f610-4204-959d-293035f4ea24","status":"closed","scheduled":"2003-01-19T20:08:15+00:00","attendance":66713,"utc_offset":-5,"entry_mode":"INGEST","venue":{"id":"905f3091-107b-4e7d-af70-2e3822c09aee","name":"Veterans Stadium","city":"Philadelphia","state":"PA","zip":"19148","address":"3501 South Broad Street","capacity":65352,"surface":"artificial","roof_type":"outdoor","sr_id":"sr:venue:1825"},"home":{"id":"386bdbf9-9eea-4869-bb9a-274b0bc66e80","name":"Philadelphia Eagles","alias":"PHI","game_number":2,"sr_id":"sr:competitor:4428"},"away":{"id":"4254d319-1bc7-4f81-b4ab-b5e6f3402b69","name":"Tampa Bay Buccaneers","alias":"TB","game_number":2,"sr_id":"sr:competitor:4388"},"scoring":{"home_points":10,"away_points":27,"periods":[{"period_type":"quarter","id":"0cb55ec6-0bdb-4968-a51f-9106c70f9216","number":1,"sequence":1,"home_points":7,"away_points":10},{"period_type":"quarter","id":"070c6635-f7e3-4c2b-8c75-f8001d1e14e8","number":2,"sequence":2,"home_points":3,"away_points":7},{"period_type":"quarter","id":"f2d526fd-739e-4b4b-9cef-15bb5b0ff77c","number":3,"sequence":3,"home_points":0,"away_points":3},{"period_type":"quarter","id":"3566cc2b-567f-4da7-809f-1310b74c337e","number":4,"sequence":4,"home_points":0,"away_points":7}]}},{"id":"f3cbd0b6-95fd-43b5-bcf0-f97ff663224e","status":"closed","scheduled":"2003-01-20T00:46:26+00:00","attendance":62544,"utc_offset":-8,"entry_mode":"INGEST","venue":{"id":"ba1ad00f-9130-462c-93f9-5612a0015117","name":"RingCentral Coliseum","city":"Oakland","state":"CA","country":"USA","zip":"94621","address":"7000 Coliseum Way","capacity":53286,"surface":"turf","roof_type":"outdoor","sr_id":"sr:venue:8095","location":{"lat":"37.750342","lng":"-122.202806"}},"home":{"id":"1c1cec48-6352-4556-b789-35304c1a6ae1","name":"Oakland Raiders","alias":"OAK","game_number":2,"sr_id":"sr:competitor:4390"},"away":{"id":"d26a1ca5-722d-4274-8f97-c92e49c96315","name":"Tennessee Titans","alias":"TEN","game_number":2,"sr_id":"sr:competitor:367364"},"scoring":{"home_points":41,"away_points":24,"periods":[{"period_type":"quarter","id":"fcc8d7bd-0d18-4c26-b554-c2a55a9b20a8","number":1,"sequence":1,"home_points":14,"away_points":7},{"period_type":"quarter","id":"e46f8827-9b8f-4d70-9563-2951d0073a3e","number":2,"sequence":2,"home_points":10,"away_points":10},{"period_type":"quarter","id":"db407da8-4e99-4f9d-9c6c-7e58fb2d1a31","number":3,"sequence":3,"home_points":3,"away_points":7},{"period_type":"quarter","id":"41cb7d2f-a9e3-42e1-bfab-1d2c5612f47d","number":4,"sequence":4,"home_points":14,"away_points":0}]}}]},{"id":"c0f55567-ae37-4271-bcf6-ec6ac8ef2ff7","sequence":4,"title":"4","games":[{"id":"d1e46cb7-52d9-4c4a-b403-974a12f3e0af","status":"closed","scheduled":"2003-01-26T23:26:53+00:00","attendance":67603,"utc_offset":-8,"entry_mode":"INGEST","venue":{"id":"7ca47702-8951-45be-a4f5-3e7d78f8f399","name":"Qualcomm Stadium","city":"San Diego","state":"CA","country":"USA","zip":"92108","address":"9449 Friars Road","capacity":70561,"surface":"turf","roof_type":"outdoor","sr_id":"sr:venue:30957"},"home":{"id":"4254d319-1bc7-4f81-b4ab-b5e6f3402b69","name":"Tampa Bay Buccaneers","alias":"TB","game_number":3,"sr_id":"sr:competitor:4388"},"away":{"id":"1c1cec48-6352-4556-b789-35304c1a6ae1","name":"Oakland Raiders","alias":"OAK","game_number":3,"sr_id":"sr:competitor:4390"},"scoring":{"home_points":48,"away_points":21,"periods":[{"period_type":"quarter","id":"9eff693a-17b8-44fb-874f-be30ce4093d9","number":1,"sequence":1,"home_points":3,"away_points":3},{"period_type":"quarter","id":"bd4f5d25-38ef-45fe-86a8-65b12ec39758","number":2,"sequence":2,"home_points":17,"away_points":0},{"period_type":"quarter","id":"588cd316-dd3d-4e73-aa51-93e87f60d67c","number":3,"sequence":3,"home_points":14,"away_points":6},{"period_type":"quarter","id":"3fe07586-4dd1-49c9-b0f0-e3747dc28d50","number":4,"sequence":4,"home_points":14,"away_points":12}]}}]}],"_comment":"Generation started @ 2023-01-21 02:17:36 UTC ended @ 2023-01-21 02:17:36 UTC"}